{
    "Communicative Disorders": 128,
    "Statistics": 140,
    "German": 120,
    "Geography": 154,
    "Social Work": 149,
    "Graphic Design": 118,
    "Nursing": 124,
    "Human Resources/Personnel Management": 97,
    "Pre-Nursing & Nursing RN-BS": 79,
    "Accounting": 89,
    "Chemistry": 143,
    "Music": 116,
    "Music - Performance": 115,
    "Radiologic Science & Technology": 130,
    "Manufacturing Engineering": 111,
    "Marketing": 94,
    "Jewish Studies": 137,
    "Production and Operations Management": 92,
    "Radio/Television/Broadcast": 100,
    "Deaf Studies": 150,
    "Athletic Training": 105,
    "Medical Technology": 129,
    "Anthropology": 151,
    "Linguistics": 133,
    "Liberal Studies": 162,
    "Biomedical Physics": 84,
    "Earth Science": 145,
    "Construction Engineering Technology": 112,
    "Women's Studies": 160,
    "Microbiology": 82,
    "African-American Studies": 157,
    "English": 132,
    "Computer Science and Information Technology": 101,
    "Latin/Central American Studies": 80,
    "Cell and Molecular Biology": 85,
    "Philosophy": 135,
    "Civil Engineering": 107,
    "Theatre Arts": 117,
    "Mechanical Engineering": 110,
    "Humanities": 138,
    "Public Health": 125,
    "International Business": 96,
    "Business Administration": 87,
    "Biology": 81,
    "Mexican-American Studies": 158,
    "Environmental and Occupational Health": 127,
    "Business Law": 98,
    "Health Care Management/Administration": 123,
    "Dietetics/Nutritional Science": 131,
    "Speech Communication": 134,
    "Psychology": 146,
    "Hospitality": 147,
    "Health Education": 126,
    "Child Development": 103,
    "Journalism": 99,
    "Cinema/Film": 119,
    "Business Education": 88,
    "Finance": 90,
    "Art": 113,
    "Mathematics": 139,
    "Kinesiology": 104,
    "Geology": 144,
    "Religious Studies": 136,
    "Urban Studies": 159,
    "Real Estate": 95,
    "Environmental Biology & Ecology": 86,
    "Electrical Engineering": 108,
    "Political Science": 155,
    "Health Science": 122,
    "Economics": 152,
    "Information Systems": 102,
    "Physics": 142,
    "Spanish": 121,
    "Recreation Management & Administration": 148,
    "Sociology": 156,
    "Asian/Asian-American Studies": 161,
    "Computer Engineering": 109,
    "Engineering": 106,
    "Applied Mathematics": 141,
    "Management": 91,
    "Management Systems Analysis / Operations Research": 93,
    "Art History": 114,
    "History": 153,
    "Biochemistry": 83
}