{
    "70": {
        "21025": 70,
        "6031": 23,
        "19051": 66,
        "11051": 44,
        "12032": 1,
        "22021": 74,
        "15061": 57,
        "49012": 85,
        "5131": 19,
        "49993": 86,
        "9081": 30,
        "5995": 21,
        "22081": 79,
        "4111": 4,
        "22051": 76,
        "12253": 53,
        "17011": 62,
        "3085": 2,
        "4152": 6,
        "19021": 65,
        "19141": 67,
        "4171": 7,
        "6022": 22,
        "17031": 64,
        "9101": 33,
        "22111": 80,
        "8375": 28,
        "19171": 68,
        "5062": 14,
        "12031": 47,
        "5041": 12,
        "10031": 37,
        "15051": 56,
        "5064": 15,
        "4011": 3,
        "12140": 48,
        "21031": 71,
        "7021": 25,
        "12142": 50,
        "22041": 75,
        "21041": 72,
        "5011": 9,
        "5072": 16,
        "11031": 43,
        "4141": 5,
        "22996": 84,
        "4201": 8,
        "15102": 60,
        "5021": 11,
        "5111": 18,
        "20011": 69,
        "9094": 32,
        "8231": 26,
        "9091": 31,
        "9134": 34,
        "5012": 10,
        "15101": 59,
        "15091": 58,
        "12231": 52,
        "12201": 51,
        "9011": 29,
        "8351": 27,
        "9254": 35,
        "22061": 77,
        "12021": 46,
        "22141": 82,
        "7012": 24,
        "15991": 61,
        "22071": 78,
        "10091": 41,
        "17021": 63,
        "10071": 40,
        "10101": 42,
        "12141": 49,
        "21044": 73,
        "5061": 13,
        "5091": 17,
        "49991": 83,
        "12011": 45,
        "13061": 54,
        "10041": 38,
        "22131": 81,
        "10051": 39,
        "10021": 36,
        "15011": 55,
        "5151": 20
    },
    "0": {
        "9251": 154,
        "5064": 115,
        "20991": 213,
        "9256": 157,
        "5171": 123,
        "7028": 130,
        "6031": 127,
        "4021": 102,
        "12221": 188,
        "11013": 174,
        "9013": 141,
        "4991": 109,
        "10091": 172,
        "8225": 132,
        "12032": 86,
        "2021": 92,
        "6041": 245,
        "22997": 236,
        "15061": 198,
        "4101": 242,
        "5131": 121,
        "1993": 91,
        "1043": 88,
        "1091": 87,
        "22994": 248,
        "9061": 144,
        "9081": 145,
        "8232": 133,
        "22993": 234,
        "22991": 233,
        "5995": 124,
        "4071": 103,
        "22081": 228,
        "8375": 136,
        "9131": 150,
        "49081": 241,
        "9255": 156,
        "5083": 118,
        "22051": 225,
        "12253": 190,
        "13031": 192,
        "9259": 159,
        "22011": 222,
        "17011": 204,
        "10015": 161,
        "4152": 106,
        "49017": 238,
        "20013": 212,
        "9254": 155,
        "19021": 207,
        "10022": 162,
        "8393": 137,
        "19141": 210,
        "4171": 107,
        "9151": 153,
        "6022": 126,
        "10082": 171,
        "12232": 189,
        "9101": 149,
        "22111": 229,
        "19025": 208,
        "15091": 200,
        "15031": 195,
        "19171": 211,
        "5111": 120,
        "22063": 226,
        "8357": 135,
        "10031": 165,
        "5061": 114,
        "15051": 197,
        "49011": 237,
        "10025": 164,
        "10071": 168,
        "4011": 100,
        "2031": 93,
        "12140": 183,
        "9093": 147,
        "4181": 108,
        "10101": 173,
        "22021": 223,
        "21031": 216,
        "5041": 113,
        "19051": 209,
        "12201": 186,
        "7021": 131,
        "12142": 185,
        "22041": 224,
        "9133": 151,
        "3085": 97,
        "5011": 110,
        "21021": 215,
        "3071": 96,
        "22999": 235,
        "12081": 182,
        "11031": 176,
        "3131": 99,
        "4141": 105,
        "12204": 187,
        "3122": 98,
        "4201": 101,
        "15011": 194,
        "5021": 112,
        "9051": 143,
        "13061": 193,
        "49021": 239,
        "4111": 104,
        "9094": 148,
        "8392": 129,
        "9091": 146,
        "9134": 152,
        "5012": 111,
        "10052": 246,
        "2041": 94,
        "15101": 201,
        "15021": 247,
        "13011": 191,
        "9257": 158,
        "9021": 142,
        "8351": 134,
        "5992": 243,
        "1131": 90,
        "20993": 214,
        "11021": 175,
        "5081": 117,
        "9262": 160,
        "15041": 196,
        "8396": 140,
        "21991": 221,
        "5997": 244,
        "12021": 181,
        "5072": 116,
        "22141": 231,
        "15991": 203,
        "22071": 227,
        "11051": 177,
        "17021": 205,
        "21041": 217,
        "1121": 89,
        "10081": 170,
        "6011": 125,
        "17031": 206,
        "0": 85,
        "12141": 184,
        "21044": 219,
        "15071": 199,
        "11071": 178,
        "8395": 139,
        "8394": 138,
        "5091": 119,
        "49991": 232,
        "12011": 180,
        "10072": 169,
        "10023": 163,
        "11081": 179,
        "10041": 166,
        "22131": 230,
        "10051": 167,
        "49051": 240,
        "6991": 128,
        "2061": 95,
        "21051": 220,
        "21042": 218,
        "15102": 202,
        "5151": 122
    }
}