[
    {
        "majors": "Nursing",
        "id": 2,
        "hegis_at_exit": 121,
        "entry_status": "FTF + FTT",
        "student_path": 1,
        "campus": "10 + 40 + 45 + 50 + 55 + 70 + 73"
    },
    {
        "majors": "Agriculture/Agricultural Science & Horticulture",
        "id": 3,
        "hegis_at_exit": 1011,
        "entry_status": "FTF + FTT",
        "student_path": 1,
        "campus": "10 + 40 + 45 + 50 + 55 + 70 + 73"
    },
    {
        "majors": "Agriculture/Agricultural Science & Horticulture",
        "id": 4,
        "hegis_at_exit": 1041,
        "entry_status": "FTF + FTT",
        "student_path": 1,
        "campus": "10 + 40 + 45 + 50 + 55 + 70 + 73"
    },
    {
        "majors": "Education",
        "id": 48,
        "hegis_at_exit": 8011,
        "entry_status": "FTF + FTT",
        "student_path": 1,
        "campus": "10 + 40 + 45 + 50 + 55 + 70 + 73"
    },
    {
        "majors": "Speech Language Pathology",
        "id": 103,
        "hegis_at_exit": 12204,
        "entry_status": "FTF + FTT",
        "student_path": 1,
        "campus": "10 + 40 + 45 + 50 + 55 + 70 + 73"
    },
    {
        "majors": "Psychology",
        "id": 128,
        "hegis_at_exit": 20011,
        "entry_status": "FTF + FTT",
        "student_path": 1,
        "campus": "10 + 40 + 45 + 50 + 55 + 70 + 73"
    },
    {
        "majors": "Recreation Management & Administration",
        "id": 132,
        "hegis_at_exit": 21025,
        "entry_status": "FTF + FTT",
        "student_path": 1,
        "campus": "10 + 40 + 45 + 50 + 55 + 70 + 73"
    },
    {
        "majors": "Recreation Management & Administration",
        "id": 133,
        "hegis_at_exit": 21031,
        "entry_status": "FTF + FTT",
        "student_path": 1,
        "campus": "10 + 40 + 45 + 50 + 55 + 70 + 73"
    },
    {
        "majors": "Women's Studies",
        "id": 149,
        "hegis_at_exit": 22990,
        "entry_status": "FTF + FTT",
        "student_path": 1,
        "campus": "10 + 40 + 45 + 50 + 55 + 70 + 73"
    },
    {
        "majors": "Women's Studies",
        "id": 152,
        "hegis_at_exit": 22996,
        "entry_status": "FTF + FTT",
        "student_path": 1,
        "campus": "10 + 40 + 45 + 50 + 55 + 70 + 73"
    },
    {
        "majors": "Women's Studies",
        "id": 155,
        "hegis_at_exit": 49012,
        "entry_status": "FTF + FTT",
        "student_path": 1,
        "campus": "10 + 40 + 45 + 50 + 55 + 70 + 73"
    },
    {
        "majors": "Education",
        "id": 159,
        "hegis_at_exit": 49081,
        "entry_status": "FTF + FTT",
        "student_path": 1,
        "campus": "10 + 40 + 45 + 50 + 55 + 70 + 73"
    },
    {
        "majors": "Psychology",
        "id": 167,
        "hegis_at_exit": 20013,
        "entry_status": "FTF + FTT",
        "student_path": 3,
        "campus": "10 + 40 + 45 + 50 + 55 + 70 + 73"
    },
    {
        "majors": "Nursing",
        "id": 191,
        "hegis_at_exit": 12031,
        "entry_status": "Postbacc",
        "student_path": 5,
        "campus": "10 + 40 + 45 + 50 + 55 + 70 + 73"
    },
    {
        "majors": "Speech Language Pathology",
        "id": 195,
        "hegis_at_exit": 12203,
        "entry_status": "Postbacc",
        "student_path": 5,
        "campus": "10 + 40 + 45 + 50 + 55 + 70 + 73"
    }
]